{
  "dct_title_s": "Map of the District of Columbia, showing location of schools.",
  "dct_language_sm": [
    "eng"
  ],
  "schema_provider_s": "Michigan State University",
  "gbl_resourceClass_sm": [
    "Maps"
  ],
  "dcat_keyword_sm": [
    "Michigan State University Map Library"
  ],
  "dct_temporal_sm": [
    "1906"
  ],
  "gbl_indexYear_im": [
    "1906"
  ],
  "gbl_dateRange_drsim": [
    "[1906 TO 1906]"
  ],
  "dct_spatial_sm": [
    "D.C.--Washington"
  ],
  "locn_geometry": "POLYGON((-77.1198 38.9955, -76.9094 38.9955, -76.9094 38.7916, -77.1198 38.7916, -77.1198 38.9955))",
  "dcat_bbox": "ENVELOPE(-77.12,-76.91,39.00,38.79)",
  "dcat_centroid": "38.894999999999996,-77.015",
  "pcdm_memberOf_sm": [
    "64bd8c4c-8e60-4956-b43d-bdc3f93db488"
  ],
  "dct_isPartOf_sm": [
    "06d-01"
  ],
  "dct_accessRights_s": "Public",
  "dct_format_s": "JPEG",
  "dct_references_s": "{\"http://schema.org/url\":\"https://lib.msu.edu/branches/maps/MSU-Scanned/UnitedStates/822-C-1906-schools\",\"http://schema.org/downloadUrl\":[{\"url\":\"https://archive.lib.msu.edu/maps/MSU-Scanned/UnitedStates/822-C-1906-schools.jpg\",\"label\":\"JPEG\"}]}",
  "id": "3a1fb630-8e6b-4a10-b3a2-97435190ef77",
  "dct_identifier_sm": [
    "3a1fb630-8e6b-4a10-b3a2-97435190ef77"
  ],
  "gbl_mdVersion_s": "Aardvark"
}