{
  "dct_title_s": "Official county map, Mecosta County, Michigan",
  "dct_description_sm": [
    "Extent: 1 map ",
    " Abstract: County road map. ",
    " Notes: Date of publication inferred from date of acquisition.",
    "Includes text and index to county roads.",
    "Scale determined from section lines."
  ],
  "dct_language_sm": [
    "eng"
  ],
  "dct_creator_sm": [
    "Mecosta County Road Commission",
    "Cadillac Printing Company"
  ],
  "dct_publisher_sm": [
    "Mecosta County Road Commission"
  ],
  "schema_provider_s": "Michigan State University",
  "gbl_resourceClass_sm": [
    "Maps"
  ],
  "dct_subject_sm": [
    "Roads"
  ],
  "dct_temporal_sm": [
    "1966"
  ],
  "dct_issued_s": "1966",
  "gbl_indexYear_im": [
    "1966"
  ],
  "gbl_dateRange_drsim": [
    "[1966 TO 1966]"
  ],
  "dct_spatial_sm": [
    "Michigan--Mecosta County",
    "Michigan"
  ],
  "locn_geometry": "POLYGON((-85.5642 43.8142, -85.0844 43.8142, -85.0844 43.4658, -85.5642 43.4658, -85.5642 43.8142))",
  "dcat_bbox": "ENVELOPE(-85.56,-85.08,43.81,43.47)",
  "dcat_centroid": "43.64,-85.32",
  "pcdm_memberOf_sm": [
    "dc8c18df-7d64-4ff4-a754-d18d0891187d"
  ],
  "dct_isPartOf_sm": [
    "06d-01"
  ],
  "dct_rights_sm": [
    "Creative Commons Public Domain Mark 1.0: This work has been identified as being free of known restrictions under copyright law, including all related and neighboring rights. You can copy, modify, distribute and perform the work, even for commercial purposes, all without asking permission."
  ],
  "dct_accessRights_s": "Public",
  "dct_format_s": "TIFF/JPEG",
  "dct_references_s": "{\"http://schema.org/url\":\"https://d.lib.msu.edu/maps/1117\",\"http://schema.org/downloadUrl\":[{\"url\":\"https://d.lib.msu.edu/maps/1117/JPG/download\",\"label\":\"JPEG\"},{\"url\":\"https://d.lib.msu.edu/maps/1117/OBJ/download\",\"label\":\"TIFF\"}],\"http://iiif.io/api/presentation#manifest\":\"https://d.lib.msu.edu/maps/1117/manifest\"}",
  "id": "ark-85335-m56972q37",
  "dct_identifier_sm": [
    "oai:d.lib.msu.edu:maps_1117",
    "https://n2t.net/ark:/85335/m56972q37"
  ],
  "gbl_mdVersion_s": "Aardvark"
}